codigos-manual-verilog/circuito-secuencial/mef.v
module mef (
            // reloj y reset
            input clk,
            input rst,

            // entradas
            input A,
            input B,

            // salidas (como vamos a usar codigo procedural, hay que declarar la salida como reg)
            output reg Z,

            // depuración
            output [2:0] estado_depurado
           );

// senales internas
reg [2:0] estado;
reg [2:0] estado_siguiente; 

// asignacion de variables de estado a parametros
parameter [2:0] INIT = 3'b000,
                A0 = 3'b001,
                A1 = 3'b010,
                OK0 = 3'b011,
                OK1 = 3'b100;

// comportamiento del estado siguiente
always @(*) begin
    case(estado)
        INIT: if (A == 0) estado_siguiente = A0;
              else estado_siguiente = A1;
        A0: if (A == 0) estado_siguiente = OK0;
            else estado_siguiente = A1;
        A1: if (A == 0) estado_siguiente = A0;
            else estado_siguiente = OK1;
        OK0: if (A == 0) estado_siguiente = OK0;
             else if ((A == 0) && (B == 1)) estado_siguiente = OK1;
             else estado_siguiente = A1;
        OK1: if ((A == 0) && (B == 0)) estado_siguiente = A0;
        else if ((A == 0) && (B == 1)) estado_siguiente = OK0;
        else estado_siguiente = OK1;
        default: estado_siguiente = INIT;
    endcase
end

// logica de salida
always @(estado) begin
    case(estado)
        INIT: Z = 0;
        A0: Z = 0;
        A1: Z = 0;
        OK0: Z = 1;
        OK1: Z = 1;
        default: Z = 0;
    endcase
end

// memoria de estado
always @(posedge clk) begin
    if(rst)
        estado <= 0;
    else
        estado <= estado_siguiente;
end

// depuración
assign estado_depurado = estado;

endmodule

codigos-manual-verilog/circuito-secuencial/waveform.vcd
$version Generated by VerilatedVcd $end
$date Tue Dec 19 15:35:00 2023
 $end
$timescale   1ps $end

 $scope module TOP $end
  $var wire  1 % A $end
  $var wire  1 & B $end
  $var wire  1 ' Z $end
  $var wire  1 # clk $end
  $var wire  3 ( estado_depurado [2:0] $end
  $var wire  1 $ rst $end
  $scope module mef $end
   $var wire  1 % A $end
   $var wire  3 , A0 [2:0] $end
   $var wire  3 - A1 [2:0] $end
   $var wire  1 & B $end
   $var wire  3 + INIT [2:0] $end
   $var wire  3 . OK0 [2:0] $end
   $var wire  3 / OK1 [2:0] $end
   $var wire  1 ' Z $end
   $var wire  1 # clk $end
   $var wire  3 ) estado [2:0] $end
   $var wire  3 ( estado_depurado [2:0] $end
   $var wire  3 * estado_siguiente [2:0] $end
   $var wire  1 $ rst $end
  $upscope $end
 $upscope $end
$enddefinitions $end


#0
1#
0$
0%
ÿ&
0'
b001 (
b001 )
b011 *
b000 +
b001 ,
b010 -
b011 .
b100 /
#1
ÿ%
0&
b000 (
b000 )
b000 *
#2
ÿ&
#3
0%
0&
#4
ÿ&
b001 (
b001 )
b011 *
#5
ÿ%
0&
b000 (
b000 )
b000 *
#6
ÿ&
#7
0%
0&
#8
ÿ&
b001 (
b001 )
b011 *
#9
ÿ%
0&
b000 (
b000 )
b000 *
#10
ÿ&
#11
0%
0&
#12
ÿ&
b001 (
b001 )
b011 *
#13
ÿ%
0&
b000 (
b000 )
b000 *
#14
ÿ&
#15
0%
0&
#16
ÿ&
b001 (
b001 )
b011 *
#17
ÿ%
0&
b000 (
b000 )
b000 *
#18
ÿ&
#19
0%
0&
